infi.instruct-0.6.33-py2.7-nspkg.pth
infi/instruct/__init__.py
infi/instruct/__version__.py
infi/instruct/_compat.py
infi/instruct/array.py
infi/instruct/array_macros.py
infi/instruct/base.py
infi/instruct/errors.py
infi/instruct/macros.py
infi/instruct/mapping.py
infi/instruct/mapping_macros.py
infi/instruct/numeric.py
infi/instruct/numeric_macros.py
infi/instruct/padding.py
infi/instruct/string.py
infi/instruct/string_macros.py
infi/instruct/struct_macros.py
infi/instruct/buffer/__init__.py
infi/instruct/buffer/buffer.py
infi/instruct/buffer/compat.py
infi/instruct/buffer/field_reference_builder.py
infi/instruct/buffer/io_buffer.py
infi/instruct/buffer/macros.py
infi/instruct/buffer/range.py
infi/instruct/buffer/serialize.py
infi/instruct/buffer/reference/__init__.py
infi/instruct/buffer/reference/after_field.py
infi/instruct/buffer/reference/builtins.py
infi/instruct/buffer/reference/contexts.py
infi/instruct/buffer/reference/field.py
infi/instruct/buffer/reference/field_or_attr.py
infi/instruct/buffer/reference/func_call.py
infi/instruct/buffer/reference/range.py
infi/instruct/buffer/reference/reference.py
infi/instruct/buffer/reference/total_size.py
infi/instruct/struct/__init__.py
infi/instruct/struct/bit.py
infi/instruct/struct/const.py
infi/instruct/struct/lazy.py
infi/instruct/struct/optional.py
infi/instruct/struct/pointer.py
infi/instruct/struct/selector.py
infi/instruct/utils/__init__.py
infi/instruct/utils/bitstringio.py
infi/instruct/utils/kwargs.py
infi/instruct/utils/read_ahead_stream.py
infi/instruct/utils/safe_repr.py
infi.instruct-0.6.33.dist-info/LICENSE
infi.instruct-0.6.33.dist-info/METADATA
infi.instruct-0.6.33.dist-info/WHEEL
infi.instruct-0.6.33.dist-info/entry_points.txt
infi.instruct-0.6.33.dist-info/namespace_packages.txt
infi.instruct-0.6.33.dist-info/top_level.txt
infi.instruct-0.6.33.dist-info/RECORD
