Metadata-Version: 2.1
Name: infi.instruct
Version: 0.6.33
Summary: declarative structure marshalling
Home-page: https://github.com/Infinidat/infi.instruct
Author: Arnon Yaari
Author-email: arnony@infinidat.com
License: BSD
Platform: UNKNOWN
Classifier: Intended Audience :: Developers
Classifier: Intended Audience :: System Administrators
Classifier: License :: OSI Approved :: BSD License
Classifier: Operating System :: OS Independent
Classifier: Programming Language :: Python
Classifier: Programming Language :: Python :: 2
Classifier: Programming Language :: Python :: 3
Classifier: Topic :: Software Development :: Libraries :: Python Modules
Requires-Dist: infi.exceptools (>=0.2.1)
Requires-Dist: setuptools
Requires-Dist: six
